admin_view/__init__.py
admin_view/admin.py
admin_view/apps.py
admin_view/changelist.py
admin_view/decorators.py
admin_view/mixins/__init__.py
admin_view/mixins/admin.py
admin_view/mixins/views.py
admin_view/report/__init__.py
admin_view/report/filters.py
admin_view/report/views.py
admin_view/templates/admin/custom_view/base_custom_view.html
admin_view/templates/admin/custom_view/change_form.html
admin_view/templates/admin/custom_view/custom_view.html
admin_view/templates/admin/custom_view/example.html
admin_view/templates/admin/custom_view/report.html
admin_view/templates/admin/custom_view/change_form/change_form.html
admin_view/templates/admin/custom_view/change_form/readonly_view.html
admin_view/templates/admin/custom_view/includes/_pagination.html
admin_view/templatetags/__init__.py
admin_view/templatetags/admin_helpers.py
admin_view/utils/__init__.py
admin_view/utils/dt.py
admin_view/views/__init__.py
admin_view/views/base.py
admin_view/views/generics.py
django_admin_view-0.0.2.dist-info/LICENSE
django_admin_view-0.0.2.dist-info/METADATA
django_admin_view-0.0.2.dist-info/WHEEL
django_admin_view-0.0.2.dist-info/top_level.txt
django_admin_view-0.0.2.dist-info/RECORD
